ergiq_fixer/__init__.py
ergiq_fixer/__main__.py
ergiq_fixer/fitfixer.py
ergiq_fixer-1.1.0.dist-info/entry_points.txt
ergiq_fixer-1.1.0.dist-info/LICENSE
ergiq_fixer-1.1.0.dist-info/WHEEL
ergiq_fixer-1.1.0.dist-info/METADATA
ergiq_fixer-1.1.0.dist-info/RECORD
