Metadata-Version: 2.1
Name: ergiq-fixer
Version: 1.1.0
Summary: Parses raw fit files created by ErgIQ and exports to TCX with merged HR data.
License: GPL-3.0-or-later
Author: Kristian Berg
Author-email: kriberg@tihlde.org
Requires-Python: >=3.6,<4.0
Classifier: License :: OSI Approved :: GNU General Public License v3 or later (GPLv3+)
Classifier: Programming Language :: Python :: 3
Classifier: Programming Language :: Python :: 3.6
Classifier: Programming Language :: Python :: 3.7
Classifier: Programming Language :: Python :: 3.8
Requires-Dist: click (>=7.1.2,<8.0.0)
Requires-Dist: fitparse (>=1.2.0,<2.0.0)
Requires-Dist: pytz (>=2020.1,<2021.0)
